ckanext/__init__.py
ckanext/comments/__init__.py
ckanext/comments/config.py
ckanext/comments/config_declaration.yaml
ckanext/comments/exceptions.py
ckanext/comments/helpers.py
ckanext/comments/plugin.py
ckanext/comments/signals.py
ckanext/comments/subject.py
ckanext/comments/utils.py
ckanext/comments/assets/webassets.yml
ckanext/comments/assets/css/comments-thread.css
ckanext/comments/assets/js/comments-thread.js
ckanext/comments/assets/less/comments-thread.less
ckanext/comments/logic/__init__.py
ckanext/comments/logic/action.py
ckanext/comments/logic/auth.py
ckanext/comments/logic/schema.py
ckanext/comments/logic/validators.py
ckanext/comments/migration/comments/alembic.ini
ckanext/comments/migration/comments/env.py
ckanext/comments/migration/comments/script.py.mako
ckanext/comments/migration/comments/versions/275515c51af1_init_tables.py
ckanext/comments/migration/comments/versions/910f3d575038_add_cascade_to_comments.py
ckanext/comments/migration/comments/versions/acd1862c2e17_add_extras_column_to_comments_table.py
ckanext/comments/model/__init__.py
ckanext/comments/model/base.py
ckanext/comments/model/comment.py
ckanext/comments/model/dictize.py
ckanext/comments/model/thread.py
ckanext/comments/templates/comments/snippets/comment.html
ckanext/comments/templates/comments/snippets/comment_form.html
ckanext/comments/templates/comments/snippets/comments_list.html
ckanext/comments/templates/comments/snippets/confirmation.html
ckanext/comments/templates/comments/snippets/thread.html
ckanext/comments/templates/package/read.html
ckanext/comments/tests/__init__.py
ckanext/comments/tests/conftest.py
ckanext/comments/tests/factories.py
ckanext/comments/tests/test_helpers.py
ckanext/comments/tests/test_plugin.py
ckanext/comments/tests/logic/__init__.py
ckanext/comments/tests/logic/test_action.py
ckanext/comments/tests/logic/test_auth.py
ckanext/comments/tests/logic/test_validators.py
ckanext/comments/tests/model/__init__.py
ckanext/comments/tests/model/test_comment.py
ckanext_comments-0.3.1.post1.dist-info/LICENSE
ckanext_comments-0.3.1.post1.dist-info/METADATA
ckanext_comments-0.3.1.post1.dist-info/WHEEL
ckanext_comments-0.3.1.post1.dist-info/entry_points.txt
ckanext_comments-0.3.1.post1.dist-info/top_level.txt
ckanext_comments-0.3.1.post1.dist-info/RECORD
